MANIFEST.in
README.md
requirements.txt
setup.py
django_simple_workflow/__init__.py
django_simple_workflow/admin.py
django_simple_workflow/apps.py
django_simple_workflow/models.py
django_simple_workflow/tests.py
django_simple_workflow/views.py
django_simple_workflow.egg-info/PKG-INFO
django_simple_workflow.egg-info/SOURCES.txt
django_simple_workflow.egg-info/dependency_links.txt
django_simple_workflow.egg-info/not-zip-safe
django_simple_workflow.egg-info/requires.txt
django_simple_workflow.egg-info/top_level.txt
django_simple_workflow/migrations/0001_initial.py
django_simple_workflow/migrations/__init__.py